rapids_build_backend/__init__.py
rapids_build_backend/build.py
rapids_build_backend/config.py
rapids_build_backend/impls.py
rapids_build_backend/utils.py
rapids_build_backend-0.4.1.dist-info/licenses/LICENSE
rapids_build_backend-0.4.1.dist-info/METADATA
rapids_build_backend-0.4.1.dist-info/WHEEL
rapids_build_backend-0.4.1.dist-info/top_level.txt
rapids_build_backend-0.4.1.dist-info/RECORD
