Metadata-Version: 2.4
Name: rapids-build-backend
Version: 0.4.1
Summary: Custom PEP517 builder for RAPIDS
License: Apache 2.0
Project-URL: Documentation, https://github.com/rapidsai/rapids-build-backend
Project-URL: Homepage, https://github.com/rapidsai/rapids-build-backend
Project-URL: Issues, https://github.com/rapidsai/rapids-build-backend/issues
Project-URL: Source, https://github.com/rapidsai/rapids-build-backend
Classifier: Intended Audience :: Developers
Classifier: License :: OSI Approved :: Apache Software License
Classifier: Programming Language :: Python :: 3
Classifier: Topic :: Software Development :: Build Tools
License-File: LICENSE
Requires-Dist: PyYAML
Requires-Dist: packaging
Requires-Dist: rapids-dependency-file-generator<2.0.dev0,>=1.13.3
Requires-Dist: tomlkit
Provides-Extra: test
Requires-Dist: jinja2; extra == "test"
Requires-Dist: pytest; extra == "test"
Dynamic: license-file
